aac_init/__init__.py
aac_init/__main__.py
aac_init/conf/__init__.py
aac_init/conf/global_settings.py
aac_init/control_engine/__init__.py
aac_init/control_engine/controller.py
aac_init/control_engine/global_cache.py
aac_init/control_engine/metadata.json
aac_init/control_engine/metadata_loader.py
aac_init/interaction/__init__.py
aac_init/interaction/cli/__init__.py
aac_init/interaction/cli/main.py
aac_init/interaction/force_api/__init__.py
aac_init/interaction/force_api/api.py
aac_init/interaction/force_api/openresty/installation.md
aac_init/interaction/force_api/openresty/lua/config.lua
aac_init/interaction/force_api/openresty/lua/handler.lua
aac_init/interaction/force_api/openresty/lua/login.lua
aac_init/interaction/force_api/openresty/nginx.conf
aac_init/interaction/force_api/openresty/server.crt
aac_init/interaction/force_api/openresty/server.key
aac_init/log_utils/__init__.py
aac_init/log_utils/logging_tool.py
aac_init/product/__init__.py
aac_init/product/datacenter/__init__.py
aac_init/product/datacenter/data_utils.py
aac_init/product/datacenter/data_validator.py
aac_init/product/datacenter/parameters.py
aac_init/product/datacenter/scheduler.py
aac_init/product/datacenter/schemas/00-global_policy/standard_aci_fabric.yml
aac_init/product/datacenter/schemas/01-fabric_mgmt/standard_fabric_mgmt.yml
aac_init/product/datacenter/templates/03-nac_tasks/aac_ansible/apic_deploy.yaml
aac_init/product/datacenter/templates/03-nac_tasks/aac_ansible/apic_test.yaml
aac_init/product/datacenter/templates/03-nac_tasks/aac_ansible/apic_validate.yaml
aac_init/product/datacenter/templates/03-nac_tasks/group_vars/aci.yaml.j2
aac_init/product/datacenter/templates/03-nac_tasks/host_vars/apic1/.gitkeep
aac_init/product/datacenter/templates/03-nac_tasks/inventory.yaml.j2
aac_init/product/datacenter/tools/__init__.py
aac_init/product/datacenter/tools/aci_switch_tool.py
aac_init/product/datacenter/tools/apic_cimc_tool.py
aac_init/product/datacenter/tools/apic_tool.py
aac_init-0.5.11.dist-info/LICENSE
aac_init-0.5.11.dist-info/METADATA
aac_init-0.5.11.dist-info/WHEEL
aac_init-0.5.11.dist-info/entry_points.txt
aac_init-0.5.11.dist-info/RECORD
