Metadata-Version: 2.3
Name: aac-init
Version: 0.5.11
Summary: 
Author: Rudy Lei
Author-email: shlei@cisco.com
Requires-Python: >=3.10,<4.0
Classifier: Programming Language :: Python :: 3
Classifier: Programming Language :: Python :: 3.10
Classifier: Programming Language :: Python :: 3.11
Classifier: Programming Language :: Python :: 3.12
Classifier: Programming Language :: Python :: 3.13
Requires-Dist: ansible-runner (>=2.4.0,<3.0.0)
Requires-Dist: click (>=8.0.4,<9.0.0)
Requires-Dist: errorhandler (>=2.0.1,<3.0.0)
Requires-Dist: importlib-metadata (>=7.1.0,<8.0.0)
Requires-Dist: jmespath (>=1.0.1,<2.0.0)
Requires-Dist: loguru (>=0.7.2,<0.8.0)
Requires-Dist: lxml (>=5.2.1,<6.0.0)
Requires-Dist: netmiko (>=4.4.0,<5.0.0)
Requires-Dist: paramiko (>=3.4.0,<4.0.0)
Requires-Dist: requests (>=2.31.0,<3.0.0)
Requires-Dist: ruamel-yaml (>0.16.10)
Requires-Dist: telnetlib3 (>=2.0.4,<3.0.0)
Requires-Dist: xmljson (>=0.2.1,<0.3.0)
Requires-Dist: yamale (>=4.0.3,<5.0.0)
